api_tabular/__init__.py
api_tabular/config_default.toml
api_tabular/core/__init__.py
api_tabular/core/data.py
api_tabular/core/error.py
api_tabular/core/health.py
api_tabular/core/query.py
api_tabular/core/sentry.py
api_tabular/core/swagger.py
api_tabular/core/url.py
api_tabular/core/utils.py
api_tabular/core/version.py
api_tabular/metrics/__init__.py
api_tabular/metrics/app.py
api_tabular/tabular/__init__.py
api_tabular/tabular/app.py
api_tabular/tabular/utils.py
udata_hydra_csvapi-0.3.1.dist-info/licenses/LICENSE
udata_hydra_csvapi-0.3.1.dist-info/METADATA
udata_hydra_csvapi-0.3.1.dist-info/WHEEL
udata_hydra_csvapi-0.3.1.dist-info/top_level.txt
udata_hydra_csvapi-0.3.1.dist-info/RECORD
