Metadata-Version: 2.4
Name: udata-hydra-csvapi
Version: 0.3.1
Summary: API for CSV converted by udata-hydra
Author-email: "data.gouv.fr" <opendatateam@data.gouv.fr>
License-Expression: MIT
Requires-Python: <3.14,>=3.11
License-File: LICENSE
Requires-Dist: aiohttp<4.0.0,>=3.13.3
Requires-Dist: aiohttp-cors<1.0.0,>=0.8.1
Requires-Dist: aiohttp-swagger<2.0.0,>=1.0.16
Requires-Dist: gunicorn<24.0.0,>=23.0.0
Requires-Dist: sentry-sdk<3.0.0,>=2.49.0
Dynamic: license-file
